ECI/__init__.py
EasyCommandInterface/__init__.py
EasyCommandInterface/classes.py
EasyCommandInterface/exceptions.py
EasyCommandInterface-1.0.0.dist-info/LICENSE
EasyCommandInterface-1.0.0.dist-info/METADATA
EasyCommandInterface-1.0.0.dist-info/WHEEL
EasyCommandInterface-1.0.0.dist-info/top_level.txt
EasyCommandInterface-1.0.0.dist-info/RECORD
