Metadata-Version: 2.1
Name: EasyCommandInterface
Version: 1.0.0
Summary: Basic Console Listener for General Use
Home-page: https://github.com/ashenguard/easycommandinterface
Author: Ashenguard
Author-email: Ashenguard@agmdev.com
License: MIT License
Platform: UNKNOWN
Classifier: Programming Language :: Python :: 3
Classifier: License :: OSI Approved :: MIT License
Classifier: Development Status :: 4 - Beta
Classifier: Operating System :: OS Independent
Requires-Python: >=3.6
